source_license_sdk/__init__.py
source_license_sdk/client.py
source_license_sdk/exceptions.py
source_license_sdk/license_validator.py
source_license_sdk/machine_identifier.py
source_license_sdk/venv/Lib/site-packages/_distutils_hack/__init__.py
source_license_sdk/venv/Lib/site-packages/_distutils_hack/override.py
source_license_sdk/venv/Lib/site-packages/build/__init__.py
source_license_sdk/venv/Lib/site-packages/build/__main__.py
source_license_sdk/venv/Lib/site-packages/build/_builder.py
source_license_sdk/venv/Lib/site-packages/build/_ctx.py
source_license_sdk/venv/Lib/site-packages/build/_exceptions.py
source_license_sdk/venv/Lib/site-packages/build/_types.py
source_license_sdk/venv/Lib/site-packages/build/_util.py
source_license_sdk/venv/Lib/site-packages/build/env.py
source_license_sdk/venv/Lib/site-packages/build/py.typed
source_license_sdk/venv/Lib/site-packages/build/util.py
source_license_sdk/venv/Lib/site-packages/build/_compat/__init__.py
source_license_sdk/venv/Lib/site-packages/build/_compat/importlib.py
source_license_sdk/venv/Lib/site-packages/build/_compat/tarfile.py
source_license_sdk/venv/Lib/site-packages/build/_compat/tomllib.py
source_license_sdk/venv/Lib/site-packages/colorama/__init__.py
source_license_sdk/venv/Lib/site-packages/colorama/ansi.py
source_license_sdk/venv/Lib/site-packages/colorama/ansitowin32.py
source_license_sdk/venv/Lib/site-packages/colorama/initialise.py
source_license_sdk/venv/Lib/site-packages/colorama/win32.py
source_license_sdk/venv/Lib/site-packages/colorama/winterm.py
source_license_sdk/venv/Lib/site-packages/colorama/tests/__init__.py
source_license_sdk/venv/Lib/site-packages/colorama/tests/ansi_test.py
source_license_sdk/venv/Lib/site-packages/colorama/tests/ansitowin32_test.py
source_license_sdk/venv/Lib/site-packages/colorama/tests/initialise_test.py
source_license_sdk/venv/Lib/site-packages/colorama/tests/isatty_test.py
source_license_sdk/venv/Lib/site-packages/colorama/tests/utils.py
source_license_sdk-1.0.0.dist-info/licenses/LICENSE
source_license_sdk-1.0.0.dist-info/METADATA
source_license_sdk-1.0.0.dist-info/WHEEL
source_license_sdk-1.0.0.dist-info/top_level.txt
source_license_sdk-1.0.0.dist-info/RECORD
