Metadata-Version: 2.4
Name: source-license-sdk
Version: 1.0.0
Summary: A Python SDK for Source-License platform license validation and activation
Home-page: https://github.com/PixelRidgeSoftworks/Source-License
Author: Source-License Team
Author-email: PixelRidge Softworks <support@pixelridgesoftworks.com>
License: GPL-3.0
Project-URL: Homepage, https://github.com/PixelRidgeSoftworks/Source-License
Project-URL: Documentation, https://github.com/PixelRidgeSoftworks/SL_Python_SDK
Project-URL: Repository, https://github.com/PixelRidgeSoftworks/SL_Python_SDK
Project-URL: Bug Tracker, https://github.com/PixelRidgeSoftworks/SL_Python_SDK/issues
Project-URL: Discord, https://discord.gg/j6v99ZPkrQ
Keywords: license,licensing,software-license,activation,validation,drm
Classifier: Development Status :: 5 - Production/Stable
Classifier: Intended Audience :: Developers
Classifier: License :: OSI Approved :: GNU General Public License v3 (GPLv3)
Classifier: Operating System :: OS Independent
Classifier: Programming Language :: Python :: 3
Classifier: Programming Language :: Python :: 3.7
Classifier: Programming Language :: Python :: 3.8
Classifier: Programming Language :: Python :: 3.9
Classifier: Programming Language :: Python :: 3.10
Classifier: Programming Language :: Python :: 3.11
Classifier: Programming Language :: Python :: 3.12
Classifier: Topic :: Software Development :: Libraries :: Python Modules
Classifier: Topic :: System :: Software Distribution
Classifier: Topic :: Security
Requires-Python: >=3.7
License-File: LICENSE
Provides-Extra: dev
Requires-Dist: pytest>=6.0; extra == "dev"
Requires-Dist: pytest-cov; extra == "dev"
Requires-Dist: black; extra == "dev"
Requires-Dist: flake8; extra == "dev"
Requires-Dist: mypy; extra == "dev"
Provides-Extra: system
Requires-Dist: psutil>=5.0.0; extra == "system"
Dynamic: author
Dynamic: home-page
Dynamic: license-file
Dynamic: requires-python
